roh/dmx/client/__init__.py
roh/dmx/client/dmx_client.py
roh/dmx/client/dmx_client_callback.py
dmx512_client-0.4.dist-info/LICENSE
dmx512_client-0.4.dist-info/METADATA
dmx512_client-0.4.dist-info/WHEEL
dmx512_client-0.4.dist-info/top_level.txt
dmx512_client-0.4.dist-info/zip-safe
dmx512_client-0.4.dist-info/RECORD
