Metadata-Version: 2.1
Name: dmx512-client
Version: 0.4
Summary: Consume DMX-512 feed over serial line (usualy over RS458 to RS232 converter)
Home-page: https://github.com/smarek/dmx-python-client
Author: Marek Sebera
Author-email: marek.sebera@gmail.com
License: Apache License, Version 2.0
Keywords: dmx dmx512
Platform: UNKNOWN
Classifier: Development Status :: 3 - Alpha
Classifier: License :: OSI Approved :: Apache Software License
Classifier: Environment :: Console
Classifier: Operating System :: POSIX :: Linux
Classifier: Typing :: Typed
Classifier: Natural Language :: English
Classifier: Programming Language :: Python :: 3.7
Requires-Python: ~=3.7
License-File: LICENSE
Requires-Dist: pyserial (>=3.5)
